protopo/__init__.py
protopo/demo.py
protopo/protopo.py
protopo-0.1.9.dist-info/LICENSE.txt
protopo-0.1.9.dist-info/METADATA
protopo-0.1.9.dist-info/WHEEL
protopo-0.1.9.dist-info/RECORD
