Metadata-Version: 2.3
Name: protopo
Version: 0.1.9
Summary: A Python package for drawing protein topology diagrams.
License: MIT
Keywords: protopo,python,protein,bioinformatics
Author: Huanan Herman Zhao
Author-email: hermanzhaozzzz@gmail.com
Requires-Python: >=3.10
Classifier: License :: OSI Approved :: MIT License
Classifier: Programming Language :: Python :: 3
Classifier: Programming Language :: Python :: 3.10
Classifier: Programming Language :: Python :: 3.11
Classifier: Programming Language :: Python :: 3.12
Classifier: Programming Language :: Python :: 3.13
Requires-Dist: matplotlib (>=3.8.1)
